{"name":"thisisManual","id":"Junit.studentsinfo.FirstSerenityTest:thisisManual","testCaseName":"Junit.studentsinfo.FirstSerenityTest","userStory":{"id":"Junit.studentsinfo.FirstSerenityTest","storyName":"First serenity test","storyClassName":"Junit.studentsinfo.FirstSerenityTest","path":"Junit.studentsinfo","type":"story"},"featureTag":{"name":"Studentsinfo/First serenity test","type":"story","displayName":"Studentsinfo/First serenity test"},"title":"Thisis manual","tags":[{"name":"Studentsinfo/First serenity test","type":"story","displayName":"Studentsinfo/First serenity test"},{"name":"manual","type":"tag","displayName":"manual"}],"startTime":"2020-10-20T18:39:54.665+11:00[Australia/Sydney]","duration":0,"projectKey":"","annotatedResult":"PENDING","isManualTestingUpToDate":false,"manual":true,"testSource":"JUnit","order":0,"result":"PENDING"}